{
  "source_file": "bac_sequence_scientifique(1).pdf",
  "year": 2026,
  "page": 21,
  "exercise_title": "التمرين الثالث - الموضوع الثاني",
  "points": "05 نقاط",
  "questions": [
    {
      "number": "1",
      "text": "لتكن f(x)=(-6x+2)/(2x-3) على ]-∞,3/2[، ولتكن المتتالية (u_n) معرفة بـ u_0=0 وu_{n+1}=f(u_n)، وΔ: y=x، ونضع v_n=(4+2u_n)/(1-2u_n) وw_n=ln(v_n). بالقراءة البيانية حدد إشارة f(x)-x على [-2,0].",
      "tag": "seq_cobweb",
      "axis": "استعمال التمثيل البياني: طريقة السلم أو Cobweb",
      "images": [
        "images/2026_sujet_2_exercice_3_cobweb.png"
      ],
      "original_text": "بالقراءة البيانية حدد إشارة f(x)-x على [-2,0].",
      "is_standalone": true,
      "source_numbers": [
        "1"
      ],
      "is_merged": false,
      "required_results": [],
      "axis_order": 7
    },
    {
      "number": "2",
      "text": "لتكن f(x)=(-6x+2)/(2x-3) على ]-∞,3/2[، ولتكن المتتالية (u_n) معرفة بـ u_0=0 وu_{n+1}=f(u_n)، وΔ: y=x، ونضع v_n=(4+2u_n)/(1-2u_n) وw_n=ln(v_n). ثم مثل بيانيا u_0,u_1,u_2,u_3 دون حسابها. ثم ضع تخمينا حول اتجاه تغير (u_n) وتقاربها.",
      "tag": "seq_cobweb",
      "axis": "استعمال التمثيل البياني: طريقة السلم أو Cobweb",
      "images": [
        "images/2026_sujet_2_exercice_3_cobweb.png"
      ],
      "original_texts": [
        "مثل بيانيا u_0,u_1,u_2,u_3 دون حسابها.",
        "ضع تخمينا حول اتجاه تغير (u_n) وتقاربها."
      ],
      "source_numbers": [
        "2-أ",
        "2-ب"
      ],
      "is_standalone": true,
      "is_merged": true,
      "required_results": [],
      "axis_order": 7
    },
    {
      "number": "3-أ",
      "text": "لتكن f(x)=(-6x+2)/(2x-3) على ]-∞,3/2[، ولتكن المتتالية (u_n) معرفة بـ u_0=0 وu_{n+1}=f(u_n)، وΔ: y=x، ونضع v_n=(4+2u_n)/(1-2u_n) وw_n=ln(v_n). برهن بالتراجع أنه لكل n: -2<u_n≤0.",
      "tag": "seq_induction",
      "axis": "الاستدلال بالتراجع",
      "images": [],
      "original_text": "برهن بالتراجع أنه لكل n: -2<u_n≤0.",
      "is_standalone": true,
      "source_numbers": [
        "3-أ"
      ],
      "is_merged": false,
      "required_results": [],
      "axis_order": 6
    },
    {
      "number": "3-ب",
      "text": "لتكن f(x)=(-6x+2)/(2x-3) على ]-∞,3/2[، ولتكن المتتالية (u_n) معرفة بـ u_0=0 وu_{n+1}=f(u_n)، وΔ: y=x، ونضع v_n=(4+2u_n)/(1-2u_n) وw_n=ln(v_n). خمن اتجاه تغير المتتالية (u_n).",
      "tag": "seq_monotonicity",
      "axis": "دراسة اتجاه التغير: تزايد أو تناقص",
      "images": [],
      "original_text": "خمن اتجاه تغير المتتالية (u_n).",
      "is_standalone": true,
      "source_numbers": [
        "3-ب"
      ],
      "is_merged": false,
      "required_results": [],
      "axis_order": 2
    },
    {
      "number": "4-أ",
      "text": "لتكن f(x)=(-6x+2)/(2x-3) على ]-∞,3/2[، ولتكن المتتالية (u_n) معرفة بـ u_0=0 وu_{n+1}=f(u_n)، وΔ: y=x، ونضع v_n=(4+2u_n)/(1-2u_n) وw_n=ln(v_n). ضع v_n=(4+2u_n)/(1-2u_n). أثبت أن (v_n) هندسية أساسها 2/7 ثم اكتب v_n بدلالة n.",
      "tag": "seq_geometric",
      "axis": "المتتالية الهندسية: الحد العام، الأساس والمجموع",
      "images": [],
      "original_text": "ضع v_n=(4+2u_n)/(1-2u_n). أثبت أن (v_n) هندسية أساسها 2/7 ثم اكتب v_n بدلالة n.",
      "is_standalone": true,
      "source_numbers": [
        "4-أ"
      ],
      "is_merged": false,
      "required_results": [],
      "axis_order": 9
    },
    {
      "number": "4-ب",
      "text": "لتكن f(x)=(-6x+2)/(2x-3) على ]-∞,3/2[، ولتكن المتتالية (u_n) معرفة بـ u_0=0 وu_{n+1}=f(u_n)، وΔ: y=x، ونضع v_n=(4+2u_n)/(1-2u_n) وw_n=ln(v_n). عبر عن u_n بدلالة n ثم احسب نهاية المتتالية. ويمكن استعمال النتائج المحسوبة التالية كمعطيات: المتتالية (v_n) هندسية أساسها 2/7 وحدها الأول v_0=4، ومنه v_n=4(2/7)^n.",
      "tag": "seq_limits",
      "axis": "نهاية المتتالية",
      "images": [],
      "original_text": "عبر عن u_n بدلالة n ثم احسب نهاية المتتالية.",
      "is_standalone": true,
      "source_numbers": [
        "4-ب"
      ],
      "is_merged": false,
      "required_results": [
        "المتتالية (v_n) هندسية أساسها 2/7 وحدها الأول v_0=4، ومنه v_n=4(2/7)^n."
      ],
      "axis_order": 4
    },
    {
      "number": "5-أ",
      "text": "لتكن f(x)=(-6x+2)/(2x-3) على ]-∞,3/2[، ولتكن المتتالية (u_n) معرفة بـ u_0=0 وu_{n+1}=f(u_n)، وΔ: y=x، ونضع v_n=(4+2u_n)/(1-2u_n) وw_n=ln(v_n). ضع w_n=ln(v_n). بين أن (w_n) حسابية مع تعيين أساسها وحدها الأول. ويمكن استعمال النتائج المحسوبة التالية كمعطيات: المتتالية (v_n) هندسية أساسها 2/7 وحدها الأول v_0=4، ومنه v_n=4(2/7)^n.",
      "tag": "seq_arithmetic",
      "axis": "المتتالية الحسابية",
      "images": [],
      "original_text": "ضع w_n=ln(v_n). بين أن (w_n) حسابية مع تعيين أساسها وحدها الأول.",
      "is_standalone": true,
      "source_numbers": [
        "5-أ"
      ],
      "is_merged": false,
      "required_results": [
        "المتتالية (v_n) هندسية أساسها 2/7 وحدها الأول v_0=4، ومنه v_n=4(2/7)^n."
      ],
      "axis_order": 8
    },
    {
      "number": "5-ب",
      "text": "لتكن f(x)=(-6x+2)/(2x-3) على ]-∞,3/2[، ولتكن المتتالية (u_n) معرفة بـ u_0=0 وu_{n+1}=f(u_n)، وΔ: y=x، ونضع v_n=(4+2u_n)/(1-2u_n) وw_n=ln(v_n). بين صيغة المجموع w_0+w_1+...+w_n. ويمكن استعمال النتائج المحسوبة التالية كمعطيات: المتتالية (v_n) هندسية أساسها 2/7 وحدها الأول v_0=4، ومنه v_n=4(2/7)^n. المتتالية (w_n) حسابية أساسها ln(2/7) وحدها الأول w_0=ln(4)، ومنه w_n=ln(4)+nln(2/7).",
      "tag": "seq_sum",
      "axis": "مجموع حدود متتالية",
      "images": [],
      "original_text": "بين صيغة المجموع w_0+w_1+...+w_n.",
      "is_standalone": true,
      "source_numbers": [
        "5-ب"
      ],
      "is_merged": false,
      "required_results": [
        "المتتالية (v_n) هندسية أساسها 2/7 وحدها الأول v_0=4، ومنه v_n=4(2/7)^n.",
        "المتتالية (w_n) حسابية أساسها ln(2/7) وحدها الأول w_0=ln(4)، ومنه w_n=ln(4)+nln(2/7)."
      ],
      "axis_order": 10
    }
  ],
  "all_questions_are_standalone": true,
  "grouping_rule": "تُدمج الأسئلة الفرعية المتتابعة التابعة لنفس الرقم ونفس المحور في سؤال واحد مستقل، مع الاحتفاظ بجميع المعطيات اللازمة داخل نص السؤال.",
  "dependency_rule": "كل سؤال مستقل: تُدرج داخله تعريفات المتتاليات والدوال، كما تُدرج النتائج العددية أو الجبرية المحسوبة في الأجزاء السابقة عندما يحتاجها السؤال."
}